{"start":"2018-12-18T11:30:24.140Z","end":"2018-12-18T11:30:53.303Z","capabilities":{"maxInstances":5,"browserName":"chrome"},"host":"127.0.0.1","port":4444,"baseUrl":"https://www.opencart.com/","framework":"cucumber","mochaOpts":{"timeout":10000},"suites":[{"name":"Open cart application","tags":[],"duration":15432,"start":"2018-12-18T11:30:37.709Z","end":"2018-12-18T11:30:53.141Z","tests":[],"hooks":[]},{"name":"Test if the open cart application verifies the error message.","tags":[],"duration":15351,"start":"2018-12-18T11:30:37.773Z","end":"2018-12-18T11:30:53.124Z","tests":[{"name":"I open the opencart url \"http://www.opencart.com\"","start":"2018-12-18T11:30:37.778Z","duration":15526,"state":"pass"},{"name":"I pause for the 1000ms","start":"2018-12-18T11:30:47.010Z","duration":6294,"state":"pass"},{"name":"the title is  \"OpenCart - Open Source Shopping Cart Solution\"","start":"2018-12-18T11:30:48.015Z","duration":5289,"state":"pass"},{"name":"I click on elem \"Login link\"","start":"2018-12-18T11:30:48.033Z","duration":5271,"state":"pass"},{"name":"I enter \"Sweetzy\" into \"userfield\"","start":"2018-12-18T11:30:51.166Z","duration":2138,"state":"pass"},{"name":"I enter \"passdummy\" into \"password-field\"","start":"2018-12-18T11:30:51.289Z","duration":2015,"state":"pass"},{"name":"I click on elem \"Login button\"","start":"2018-12-18T11:30:51.379Z","duration":1925,"state":"pass"},{"name":"I see \"Login-error-message\" into \"Info-label\"","start":"2018-12-18T11:30:53.085Z","duration":219,"state":"pass"}],"hooks":[]}],"state":{"passed":8,"failed":0,"skipped":0}}